uapi_pytorch/__init__.py
uapi_pytorch/base/__init__.py
uapi_pytorch/base/config.py
uapi_pytorch/base/model.py
uapi_pytorch/base/register.py
uapi_pytorch/base/utils/__init__.py
uapi_pytorch/base/utils/arg.py
uapi_pytorch/base/utils/dataset_checker_utils.py
uapi_pytorch/base/utils/subprocess.py
uapi_pytorch/utils/__init__.py
uapi_pytorch/utils/cache.py
uapi_pytorch/utils/flags.py
uapi_pytorch/utils/logging.py
uapi_pytorch/utils/misc.py
uapi_pytorch/utils/util.py
uapi_pytorch/utils/errors/__init__.py
uapi_pytorch/utils/errors/dataset_checker.py
uapi_pytorch/utils/errors/others.py
uapi_pytorch/zhi_hang_yuan/__init__.py
uapi_pytorch/zhi_hang_yuan/seg/__init__.py
uapi_pytorch/zhi_hang_yuan/seg/config.py
uapi_pytorch/zhi_hang_yuan/seg/dataset.py
uapi_pytorch/zhi_hang_yuan/seg/model.py
uapi_pytorch/zhi_hang_yuan/seg/register.py
uapi_pytorch/zhi_hang_yuan/seg/runner.py
uapi_pytorch/zhi_hang_yuan/seg/unet/__init__.py
uapi_pytorch/zhi_hang_yuan/seg/unet/unet_model.py
uapi_pytorch/zhi_hang_yuan/seg/unet/unet_parts.py
uapi_pytorch-0.0.2.dist-info/LICENSE
uapi_pytorch-0.0.2.dist-info/METADATA
uapi_pytorch-0.0.2.dist-info/WHEEL
uapi_pytorch-0.0.2.dist-info/top_level.txt
uapi_pytorch-0.0.2.dist-info/RECORD
