Metadata-Version: 2.1
Name: uapi-pytorch
Version: 0.0.2
Summary: pytorch model pipeline
Author: test
Author-email: test@163.com
License-File: LICENSE
